google_datacatalog_tableau_connector-0.6.2-py3.6-nspkg.pth
google/datacatalog_connectors/tableau/__init__.py
google/datacatalog_connectors/tableau/tableau2datacatalog_cli.py
google/datacatalog_connectors/tableau/prepare/__init__.py
google/datacatalog_connectors/tableau/prepare/assembled_entry_factory.py
google/datacatalog_connectors/tableau/prepare/constants.py
google/datacatalog_connectors/tableau/prepare/datacatalog_entry_factory.py
google/datacatalog_connectors/tableau/prepare/datacatalog_tag_factory.py
google/datacatalog_connectors/tableau/prepare/datacatalog_tag_template_factory.py
google/datacatalog_connectors/tableau/prepare/entry_relationship_mapper.py
google/datacatalog_connectors/tableau/scrape/__init__.py
google/datacatalog_connectors/tableau/scrape/authenticator.py
google/datacatalog_connectors/tableau/scrape/constants.py
google/datacatalog_connectors/tableau/scrape/metadata_api_constants.py
google/datacatalog_connectors/tableau/scrape/metadata_api_helper.py
google/datacatalog_connectors/tableau/scrape/metadata_scraper.py
google/datacatalog_connectors/tableau/scrape/rest_api_helper.py
google/datacatalog_connectors/tableau/sync/__init__.py
google/datacatalog_connectors/tableau/sync/dashboards_synchronizer.py
google/datacatalog_connectors/tableau/sync/datacatalog_synchronizer.py
google/datacatalog_connectors/tableau/sync/metadata_synchronizer.py
google/datacatalog_connectors/tableau/sync/sites_synchronizer.py
google/datacatalog_connectors/tableau/sync/workbooks_synchronizer.py
google_datacatalog_tableau_connector-0.6.2.dist-info/METADATA
google_datacatalog_tableau_connector-0.6.2.dist-info/WHEEL
google_datacatalog_tableau_connector-0.6.2.dist-info/entry_points.txt
google_datacatalog_tableau_connector-0.6.2.dist-info/namespace_packages.txt
google_datacatalog_tableau_connector-0.6.2.dist-info/top_level.txt
google_datacatalog_tableau_connector-0.6.2.dist-info/RECORD
